logger_slg/__init__.py
logger_slg/slg_logger.py
logger_slg/version.py
logger_slg-0.3.6.dist-info/METADATA
logger_slg-0.3.6.dist-info/WHEEL
logger_slg-0.3.6.dist-info/top_level.txt
logger_slg-0.3.6.dist-info/RECORD
