Metadata-Version: 2.1
Name: logger-slg
Version: 0.3.6
Summary: This is a description.
Home-page: UNKNOWN
License: UNKNOWN
Platform: UNKNOWN
Requires-Python: >=3.6.3
